ml_pilot/__init__.py
ml_pilot/eda/__init__.py
ml_pilot/eda/eda.py
ml_pilot/feature_engineering/__init__.py
ml_pilot/feature_engineering/feature_engineering.py
ml_pilot-0.0.3.dist-info/LICENCE.txt
ml_pilot-0.0.3.dist-info/METADATA
ml_pilot-0.0.3.dist-info/WHEEL
ml_pilot-0.0.3.dist-info/top_level.txt
ml_pilot-0.0.3.dist-info/RECORD
