Metadata-Version: 2.1
Name: ml-pilot
Version: 0.0.3
Home-page: https://github.com/ImranNazir4/msdsf22m002.git
Author: Imran Nazir
Author-email: imrnazir8@gmail.com
Classifier: Programming Language :: Python :: 3
Classifier: License :: OSI Approved :: MIT License
Classifier: Operating System :: OS Independent
License-File: LICENCE.txt
